{
  "main": {
    "id": "eefdd39f662e73fb",
    "type": "split",
    "children": [
      {
        "id": "f39793b431c97258",
        "type": "tabs",
        "children": [
          {
            "id": "771b8ee75c9fc73c",
            "type": "leaf",
            "state": {
              "type": "markdown",
              "state": {
                "file": "DI.md",
                "mode": "source",
                "source": false
              }
            }
          }
        ]
      }
    ],
    "direction": "vertical"
  },
  "left": {
    "id": "3137ae7e5b09783a",
    "type": "split",
    "children": [
      {
        "id": "4edbc8e0c6f59fd8",
        "type": "tabs",
        "children": [
          {
            "id": "04cd7d9ef327ae57",
            "type": "leaf",
            "state": {
              "type": "file-explorer",
              "state": {
                "sortOrder": "alphabetical"
              }
            }
          },
          {
            "id": "6a720e40666516ba",
            "type": "leaf",
            "state": {
              "type": "search",
              "state": {
                "query": "file:",
                "matchingCase": false,
                "explainSearch": false,
                "collapseAll": false,
                "extraContext": false,
                "sortOrder": "alphabetical"
              }
            }
          },
          {
            "id": "08b8675aa458893a",
            "type": "leaf",
            "state": {
              "type": "bookmarks",
              "state": {}
            }
          }
        ],
        "currentTab": 2
      }
    ],
    "direction": "horizontal",
    "width": 200,
    "collapsed": true
  },
  "right": {
    "id": "4c87c6aea7d9205b",
    "type": "split",
    "children": [
      {
        "id": "3282a4b5084ef4f2",
        "type": "tabs",
        "children": [
          {
            "id": "24ed458481e2004f",
            "type": "leaf",
            "state": {
              "type": "backlink",
              "state": {
                "file": "DI.md",
                "collapseAll": false,
                "extraContext": false,
                "sortOrder": "alphabetical",
                "showSearch": false,
                "searchQuery": "",
                "backlinkCollapsed": false,
                "unlinkedCollapsed": true
              }
            }
          },
          {
            "id": "a0e6cf42a3049699",
            "type": "leaf",
            "state": {
              "type": "outgoing-link",
              "state": {
                "file": "DI.md",
                "linksCollapsed": false,
                "unlinkedCollapsed": true
              }
            }
          },
          {
            "id": "a2fdfa145b8eec03",
            "type": "leaf",
            "state": {
              "type": "tag",
              "state": {
                "sortOrder": "frequency",
                "useHierarchy": true
              }
            }
          },
          {
            "id": "8983f9a0a1c3cd6a",
            "type": "leaf",
            "state": {
              "type": "outline",
              "state": {
                "file": "DI.md"
              }
            }
          }
        ]
      }
    ],
    "direction": "horizontal",
    "width": 300,
    "collapsed": true
  },
  "left-ribbon": {
    "hiddenItems": {
      "switcher:퀵 스위처 열기": false,
      "graph:그래프 뷰 열기": false,
      "canvas:새 캔버스 만들기": false,
      "daily-notes:오늘의 데일리 노트 열기": false,
      "templates:템플릿 삽입": false,
      "command-palette:명령어 팔레트 열기": false
    }
  },
  "active": "771b8ee75c9fc73c",
  "lastOpenFiles": [
    "느슨한 결합력과 인터페이스.md",
    "DI.md",
    "Servlet & Spring Web MVC.md",
    "Spring MVC.md",
    "MVC2.md",
    "MVC1.md",
    "MVC.md",
    "Spring Start.md",
    "Spring Boot Start.md",
    "Spring 소개와 학습.md",
    "무제 파일.canvas",
    "Spring Boot/무제 파일.md",
    "Spring Boot",
    "Pasted image 20240919194142.png",
    "Pasted image 20240919193717.png",
    "Pasted image 20240919193157.png",
    "Pasted image 20240919192241.png",
    "Pasted image 20240919191953.png",
    "Pasted image 20240919191606.png",
    "Pasted image 20240919191448.png",
    "Pasted image 20240919190520.png",
    "Pasted image 20240919190511.png",
    "Pasted image 20240919190441.png",
    "스프링 부트 웹개발 기초.md",
    "회원 관리 예제 - 백엔드 개발.md",
    "스프링 웹개발 기초.pdf",
    "도커.md"
  ]
}